assets/bullet_hell/enemy.py
assets/bullet_hell/enemy_bullets.py
assets/bullet_hell/main.py
assets/bullet_hell/player.py
assets/bullet_hell/player_bullets.py
assets/bullet_hell/setting.py
assets/bullet_hell/old_verisons/bullet_hell.py
assets/bullet_hell/old_verisons/enemy.py
assets/bullet_hell/old_verisons/game_start.py
assets/bullet_hell/old_verisons/main.py
assets/bullet_hell/old_verisons/player.py
assets/startup-assets/tutorial-steps/1-create-sprites/main.py
assets/startup-assets/tutorial-steps/1-create-sprites/player.py
assets/startup-assets/tutorial-steps/1-create-sprites-task/enemy.py
assets/startup-assets/tutorial-steps/1-create-sprites-task/main.py
assets/startup-assets/tutorial-steps/1-create-sprites-task/player.py
assets/startup-assets/tutorial-steps/2-basic-events/enemy.py
assets/startup-assets/tutorial-steps/2-basic-events/main.py
assets/startup-assets/tutorial-steps/2-basic-events/player.py
assets/startup-assets/tutorial-steps/2-basic-events-task1/enemy.py
assets/startup-assets/tutorial-steps/2-basic-events-task1/main.py
assets/startup-assets/tutorial-steps/2-basic-events-task1/player.py
assets/startup-assets/tutorial-steps/2-basic-events-task2/enemy.py
assets/startup-assets/tutorial-steps/2-basic-events-task2/main.py
assets/startup-assets/tutorial-steps/2-basic-events-task2/player.py
assets/startup-assets/tutorial-steps/3-loops-conditions/enemy.py
assets/startup-assets/tutorial-steps/3-loops-conditions/main.py
assets/startup-assets/tutorial-steps/3-loops-conditions/player.py
assets/startup-assets/tutorial-steps/3-loops-conditions-task1/enemy.py
assets/startup-assets/tutorial-steps/3-loops-conditions-task1/main.py
assets/startup-assets/tutorial-steps/3-loops-conditions-task1/player.py
assets/startup-assets/tutorial-steps/3-loops-conditions-task2/enemy.py
assets/startup-assets/tutorial-steps/3-loops-conditions-task2/main.py
assets/startup-assets/tutorial-steps/3-loops-conditions-task2/player.py
assets/startup-assets/tutorial-steps/4-variables/enemy.py
pyscratch_pysc-2.0.2.dist-info/METADATA
pyscratch_pysc-2.0.2.dist-info/WHEEL
pyscratch_pysc-2.0.2.dist-info/top_level.txt
pyscratch_pysc-2.0.2.dist-info/RECORD
